codeflare/__init__.py
codeflare/_version.py
codeflare/pipelines/Datamodel.py
codeflare/pipelines/Exceptions.py
codeflare/pipelines/Runtime.py
codeflare/pipelines/__init__.py
codeflare/pipelines/utils.py
codeflare/pipelines/tests/__init__.py
codeflare/pipelines/tests/test_Datamodel.py
codeflare/pipelines/tests/test_and.py
codeflare/pipelines/tests/test_helper.py
codeflare/pipelines/tests/test_multibranch.py
codeflare/pipelines/tests/test_or.py
codeflare/pipelines/tests/test_pipeline_predict.py
codeflare/pipelines/tests/test_runtime.py
codeflare/pipelines/tests/test_save_load.py
codeflare-0.1.2.dev0.dist-info/AUTHORS
codeflare-0.1.2.dev0.dist-info/LICENSE
codeflare-0.1.2.dev0.dist-info/METADATA
codeflare-0.1.2.dev0.dist-info/WHEEL
codeflare-0.1.2.dev0.dist-info/top_level.txt
codeflare-0.1.2.dev0.dist-info/RECORD
