Metadata-Version: 2.1
Name: codeflare
Version: 0.1.2.dev0
Summary: Codeflare pipelines
Home-page: https://github.com/project-codeflare/codeflare
Author: CodeFlare team
Author-email: chcost@us.ibm.com
License: Apache v2.0
Project-URL: Bug Reports, https://github.com/project-codeflare/codeflare/issues
Project-URL: Source, https://github.com/project-codeflare/codeflare
Keywords: ray pipelines
Platform: UNKNOWN
Classifier: Development Status :: 4 - Beta
Classifier: Intended Audience :: Developers
Classifier: License :: OSI Approved :: Apache Software License
Classifier: Programming Language :: Python
Classifier: Programming Language :: Python :: 3
Classifier: Programming Language :: Python :: 3 :: Only
Classifier: Operating System :: OS Independent
Classifier: Topic :: System :: Distributed Computing
Requires-Python: >=3.7
Requires-Dist: ray[default,k8s,serve] (>=1.3.0)
Requires-Dist: setuptools (>=52.0.0)
Requires-Dist: sklearn (>=0.0)
Requires-Dist: scikit-learn (>=0.24.1)
Requires-Dist: pandas (>=1.2.4)
Requires-Dist: numpy (>=1.18.5)
Requires-Dist: pickle5 (>=0.0.11)
Requires-Dist: graphviz (>=0.16)
